README.md
setup.cfg
setup.py
lambda_appconfig/__init__.py
lambda_appconfig/extension.py
localstack_extension_lambda_appconfig.egg-info/PKG-INFO
localstack_extension_lambda_appconfig.egg-info/SOURCES.txt
localstack_extension_lambda_appconfig.egg-info/dependency_links.txt
localstack_extension_lambda_appconfig.egg-info/entry_points.txt
localstack_extension_lambda_appconfig.egg-info/not-zip-safe
localstack_extension_lambda_appconfig.egg-info/requires.txt
localstack_extension_lambda_appconfig.egg-info/top_level.txt