Metadata-Version: 2.1
Name: localstack-extension-lambda-appconfig
Version: 0.1.0
Summary: LocalStack Extension: Lambda AppConfig
Home-page: https://localstack.cloud
Author: LocalStack
Author-email: support@localstack.cloud
Provides-Extra: dev
Provides-Extra: test
